tq_utils/__init__.py
tq_utils/AMR/CodeAnalyzer.py
tq_utils/AMR/__init__.py
tq_utils/AMR/analysis_module_imports.py
tq_utils/file_manager/FileManager.py
tq_utils/file_manager/__init__.py
tq_utils/graph_dot/Model.py
tq_utils/graph_dot/__init__.py
tq_utils/graph_dot/get_dot_N_png.py
tq_utils/my_json/__init__.py
tq_utils/my_json/my_json.py
tq_utils/my_pickle/__init__.py
tq_utils/my_pickle/my_pickle.py
tq_utils/profile_decorator/__init__.py
tq_utils/profile_decorator/profile_decorator.py
tq_utils/singleton/__init__.py
tq_utils/singleton/singleton_meta_class.py
tq_utils/time_util/__init__.py
tq_utils/time_util/func_time_util.py
tq_utils/time_util/timer.py
tq_utils/tq_json/__init__.py
tq_utils/tq_json/tq_json.py
tq_utils/tq_logger/__init__.py
tq_utils/tq_logger/logger.py
tq_utils/tq_pickle/__init__.py
tq_utils/tq_pickle/tq_pickle.py
tq_utils/tq_sqlite3/__init__.py
tq_utils/tq_sqlite3/sqlite3_executor.py
tq_utils/tq_xml/__init__.py
tq_utils/tq_xml/funcs.py
tq_utils/tq_yaml/__init__.py
tq_utils/tq_yaml/funcs.py
tq_utils-0.5.0.dist-info/licenses/LICENSE
tq_utils-0.5.0.dist-info/METADATA
tq_utils-0.5.0.dist-info/WHEEL
tq_utils-0.5.0.dist-info/top_level.txt
tq_utils-0.5.0.dist-info/RECORD
