Metadata-Version: 2.4
Name: tq_utils
Version: 0.5.0
Summary: Some simple utils.
Home-page: https://gitee.com/torchW/tqutils
Author: TripleQuiz
Author-email: triple_quiz@163.com
License: MIT
Keywords: python,util,file manager,singleton,timer,functon_timeout,json,logger,pickle,sqlite3,xml,yaml
Classifier: Development Status :: 3 - Alpha
Classifier: License :: OSI Approved :: MIT License
Classifier: Programming Language :: Python :: 3.6
Classifier: Programming Language :: Python :: 3.7
Classifier: Programming Language :: Python :: 3.8
Classifier: Programming Language :: Python :: 3.9
Classifier: Programming Language :: Python :: 3.10
Classifier: Programming Language :: Python :: 3.11
Classifier: Intended Audience :: Developers
Classifier: Operating System :: Microsoft :: Windows
Classifier: Natural Language :: Chinese (Simplified)
Requires-Python: >=3.6, <3.12
License-File: LICENSE
Requires-Dist: func-timeout>=4.3.5
Requires-Dist: PyYAML>=6.0.3
Dynamic: author
Dynamic: author-email
Dynamic: classifier
Dynamic: description
Dynamic: description-content-type
Dynamic: home-page
Dynamic: keywords
Dynamic: license
Dynamic: license-file
Dynamic: requires-dist
Dynamic: requires-python
Dynamic: summary
